s3_file_uploads/__init__.py
s3_file_uploads/aws.py
s3_file_uploads/constants.py
s3_file_uploads/fields.py
s3_file_uploads/models.py
s3_file_uploads/serializers.py
s3_file_uploads/urls.py
s3_file_uploads/views.py
s3_file_uploads/migrations/0001_initial.py
s3_file_uploads/migrations/0002_uploadedfile_user.py
s3_file_uploads/migrations/__init__.py
django_s3_file_upload-0.1.0.dist-info/LICENSE
django_s3_file_upload-0.1.0.dist-info/METADATA
django_s3_file_upload-0.1.0.dist-info/WHEEL
django_s3_file_upload-0.1.0.dist-info/top_level.txt
django_s3_file_upload-0.1.0.dist-info/RECORD
